README.md
setup.py
protecto_libraries.egg-info/PKG-INFO
protecto_libraries.egg-info/SOURCES.txt
protecto_libraries.egg-info/dependency_links.txt
protecto_libraries.egg-info/requires.txt
protecto_libraries.egg-info/top_level.txt
protecto_privacy_vault/__init__.py
protecto_privacy_vault/vault_operations.py