Metadata-Version: 2.1
Name: protecto-libraries
Version: 0.0.1
Summary: Tokenisation Package
Home-page: https://bitbucket.org/onedpo/privacy_vault_library/src/develop/
Author: Protecto
Author-email: developer@protecto.ai
License: MIT
Project-URL: Bug Tracker, https://bitbucket.org/onedpo/privacy_vault_library/src/develop/issues
